managecommand/__init__.py
managecommand/client.py
managecommand/config.py
managecommand/constants.py
managecommand/daemon.py
managecommand/discovery.py
managecommand/executor.py
managecommand/runner.py
managecommand/security.py
managecommand/management/__init__.py
managecommand/management/commands/__init__.py
managecommand/management/commands/managecommand.py
managecommand-0.1.0.dist-info/METADATA
managecommand-0.1.0.dist-info/WHEEL
managecommand-0.1.0.dist-info/RECORD
