Metadata-Version: 2.4
Name: managecommand
Version: 0.1.0
Summary: Run, schedule, and audit Django management commands without SSH access
Project-URL: Homepage, https://managecommand.com
Project-URL: Documentation, https://docs.managecommand.com
Project-URL: Repository, https://github.com/managecommand/managecommand-platform
Project-URL: Issues, https://github.com/managecommand/managecommand-platform/issues
Author-email: Fran Hrzenjak <fran.hrzenjak@gmail.com>
License-Expression: MIT
Keywords: automation,commands,devops,django,management
Classifier: Development Status :: 3 - Alpha
Classifier: Framework :: Django
Classifier: Framework :: Django :: 4.2
Classifier: Framework :: Django :: 5.0
Classifier: Intended Audience :: Developers
Classifier: License :: OSI Approved :: MIT License
Classifier: Operating System :: OS Independent
Classifier: Programming Language :: Python :: 3
Classifier: Programming Language :: Python :: 3.10
Classifier: Programming Language :: Python :: 3.11
Classifier: Programming Language :: Python :: 3.12
Classifier: Topic :: Software Development :: Libraries :: Python Modules
Classifier: Topic :: System :: Systems Administration
Requires-Python: >=3.10
Requires-Dist: django>=4.2
Requires-Dist: requests>=2.28
Provides-Extra: dev
Requires-Dist: pytest-django>=4.5; extra == 'dev'
Requires-Dist: pytest>=7.0; extra == 'dev'
Requires-Dist: responses>=0.23; extra == 'dev'
